pinns/__init__.py
pinns/differentiation.py
pinns/geometry.py
pinns/initial_conditions.py
pinns/training.py
pinns-0.1.0.dist-info/LICENSE
pinns-0.1.0.dist-info/METADATA
pinns-0.1.0.dist-info/WHEEL
pinns-0.1.0.dist-info/top_level.txt
pinns-0.1.0.dist-info/RECORD
