Metadata-Version: 2.1
Name: pinns
Version: 0.1.0
Summary: Solve differntial equations using neural networks
Author-email: Alexandros Mavromatis <alex38clues@gmail.com>
License: GNU General Public License v3.0 or later
Project-URL: repository, https://github.com/alexandmi/PINNs
Keywords: differential,equations,neural networks
Classifier: Intended Audience :: Developers
Classifier: Intended Audience :: Science/Research
Classifier: License :: OSI Approved :: GNU General Public License v3 or later (GPLv3+)
Classifier: Programming Language :: Python
Classifier: Programming Language :: Python :: 3.8
Classifier: Topic :: Scientific/Engineering :: Mathematics
Classifier: Topic :: Scientific/Engineering :: Physics
Requires-Python: >=3.7
License-File: LICENSE
Requires-Dist: tensorflow (>=2.9.1)
Requires-Dist: silence-tensorflow (>=1.2.0)
